{"generated_at": "2153Z 02/12/26", "type": "FeatureCollection", "features": [{"type": "Feature", "geometry": {"type": "Point", "coordinates": [-159.2544, 21.9355]}, "properties": {"type": "PIREP", "rawOb": "LIH UA /OV LIH100005/TM 2145/FL050/TP B712/SK SCT025 TOP065 ", "alt": 5000, "age": 8.5}}, {"type": "Feature", "geometry": {"type": "Point", "coordinates": [-154.9933, 19.7211]}, "properties": {"type": "PIREP", "rawOb": "ITO UA /OV ITO080001/TM 2137/FL001/TP GLF4/SK SK BKN005-TOPUNKN", "alt": 100, "age": 16.5}}, {"type": "Feature", "geometry": {"type": "Point", "coordinates": [-155.011, 19.7214]}, "properties": {"type": "PIREP", "rawOb": "ITO UA /OV ITO0080001/TM 2121/FL001/TP B712/SK /SK BKN010-TOPUNKN/RM WIND SHEAR +UKN KTS AT 300 ", "alt": 100, "age": 32.5}}, {"type": "Feature", "geometry": {"type": "Point", "coordinates": [-155.011, 19.7214]}, "properties": {"type": "PIREP", "rawOb": "ITO UA /OV ITO0300012/TM 2113/FL040/TP B712/SK TOP075/RM IN THE CLEAR OVER CABIX, BUT BUILDUPS TOWARD THE FIELD. TOPS HIGHER AT 090 OVER LAND", "alt": 4000, "age": 40.5}}, {"type": "Feature", "geometry": {"type": "Point", "coordinates": [-159.339, 21.976]}, "properties": {"type": "PIREP", "rawOb": "LIH UA /OV PHLI/TM 2058/FLDURGD/TP B717/SK BKN027", "alt": 0, "age": 55.5}}, {"type": "Feature", "geometry": {"type": "Point", "coordinates": [-159.3381, 21.9653]}, "properties": {"type": "PIREP", "rawOb": "LIH UA /OV LIH/TM 2056/FL026/TP B712/SK BASES026", "alt": 2600, "age": 57.5}}, {"type": "Feature", "geometry": {"type": "Point", "coordinates": [-154.958, 19.7205]}, "properties": {"type": "PIREP", "rawOb": "ITO UA /OV ITO080003/TM 2040/FL003/TP B712/RM CAUGHT THE FIELD 3 MILES OUT", "alt": 300, "age": 73.5}}, {"type": "Feature", "geometry": {"type": "Point", "coordinates": [-154.65, 23.0]}, "properties": {"type": "AIREP", "rawOb": "ARP UAL650 2300N 15439W 2034 F350 M50 260/030", "alt": 35000, "age": 79.5}}, {"type": "Feature", "geometry": {"type": "Point", "coordinates": [-159.3359, 21.7893]}, "properties": {"type": "PIREP", "rawOb": "LIH UA /OV MORKE/TM 2030/FL040/TP B717/SK OVC025-085", "alt": 4000, "age": 83.5}}]}