{"generated_at": "1900Z 02/14/26", "type": "FeatureCollection", "features": [{"type": "Feature", "geometry": {"type": "Point", "coordinates": [-155.222, 22.5899]}, "properties": {"type": "PIREP", "rawOb": "HNL UA /OV KOLEA/TM 1847/FL310/TP A21N/TB LGT CHOP", "alt": 31000, "age": 13.6}}, {"type": "Feature", "geometry": {"type": "Point", "coordinates": [-161.8333, 19.95]}, "properties": {"type": "AIREP", "rawOb": "ARP UAL132 1957N 16150W 1838 F280 215/032KT TB LGT TURB IC", "alt": 28000, "age": 22.6}}, {"type": "Feature", "geometry": {"type": "Point", "coordinates": [-154.958, 19.7214]}, "properties": {"type": "PIREP", "rawOb": "ITO UA /OV ITO079003/TM 1822/FL017/TP B717/SK OVC017", "alt": 1700, "age": 38.6}}, {"type": "Feature", "geometry": {"type": "Point", "coordinates": [-159.0522, 20.6647]}, "properties": {"type": "PIREP", "rawOb": "HNL UA /OV BIGZO/TM 1800/FL320/TP C17/TB MOD TURB", "alt": 32000, "age": 60.6}}, {"type": "Feature", "geometry": {"type": "Point", "coordinates": [-155.011, 19.7214]}, "properties": {"type": "PIREP", "rawOb": "ITO UA /OV 325012/TM 1750/FL055/TP B717/SK BKN010-TOPS052/WX -RA/TB NEG", "alt": 5500, "age": 70.6}}, {"type": "Feature", "geometry": {"type": "Point", "coordinates": [-160.8142, 18.4078]}, "properties": {"type": "PIREP", "rawOb": "HNL UA /OV BARKR/TM 1747/FL390/TP C17/TB MOD370-390", "alt": 39000, "age": 73.6}}, {"type": "Feature", "geometry": {"type": "Point", "coordinates": [-157.9304, 21.3083]}, "properties": {"type": "PIREP", "rawOb": "HNL UA /OV MUA/TM 1745/FL060/TP BE9L/SK BKN060", "alt": 6000, "age": 75.6}}, {"type": "Feature", "geometry": {"type": "Point", "coordinates": [-156.4719, 20.6615]}, "properties": {"type": "PIREP", "rawOb": "OGG UA /OV OGG180015/TM 1745/FL060/TP C208/TB LGT CHOP", "alt": 6000, "age": 75.6}}]}